sibr_api/__init__.py
sibr_api/base.py
sibr_api-0.3.4.dist-info/LICENSE
sibr_api-0.3.4.dist-info/METADATA
sibr_api-0.3.4.dist-info/WHEEL
sibr_api-0.3.4.dist-info/RECORD
