Metadata-Version: 2.3
Name: sibr-api
Version: 0.3.4
Summary: A base class for building robust, asynchronous API clients.
License: MIT
Author: sigvardbratlie
Author-email: sigvard.bratlie@gmail.com
Requires-Python: >=3.11
Classifier: License :: OSI Approved :: MIT License
Classifier: Programming Language :: Python :: 3
Classifier: Programming Language :: Python :: 3.11
Classifier: Programming Language :: Python :: 3.12
Classifier: Programming Language :: Python :: 3.13
Requires-Dist: aiohttp (>=3.12.15,<4.0.0)
Requires-Dist: aresponses (>=3.0.0,<4.0.0)
Requires-Dist: pandas (>=2.3.2,<3.0.0)
Requires-Dist: python-dotenv (>=1.1.1,<2.0.0)
